{
  "$schema": "../../schemas/recipe.schema.json",
  "schema_version": 1,
  "id": "00127ffe-c2b9-5f75-840a-049ab3f083eb",
  "slug": "coconut-buko-pie-recipe",
  "name": "Buko Pie",
  "recipe_type": "dessert",
  "brief_description": "This is a recipe for Buko Pie",
  "cuisine": "Filipino",
  "instructions": [
    {
      "position": 1,
      "text": "Create the crust. Combine flour and salt then mix using a balloon whisk. Add butter and shortening then mix using a pastry mixer. Gradually add cold water a tablespoon at a time while mixing the ingredients. When everything is completely mixed, gather the mixture and divide into two equal parts. In a flat surface flatten each of the dough and roll using a rolling pin until wide enough to fit an eight or nine inch cake pan. Note: Sprinkle flour over the flat surface to prevent the dough from sticking or use a silicon mat. Arrange the first dough over the cake pan. This will be the base. Set the second flattened dough aside. This will be needed after arranging the filling in the cake pan."
    },
    {
      "position": 2,
      "text": "Make the filling by heating a saucepan and pour-in the milk. Let boil."
    },
    {
      "position": 3,
      "text": "Add the granulated white sugar and stir."
    },
    {
      "position": 4,
      "text": "Put-in the young coconut meat and cook for 3 minutes."
    },
    {
      "position": 5,
      "text": "Pour-in the cornstarch diluted in young coconut water and stir thoroughly while cooking. Cook until the texture thickens."
    },
    {
      "position": 6,
      "text": "Turn-off the heat and allow the mixture to cool down."
    },
    {
      "position": 7,
      "text": "Preheat oven to 375 degrees Fahrenheit."
    },
    {
      "position": 8,
      "text": "Arrange the cooked filling in the cake pan."
    },
    {
      "position": 9,
      "text": "Put the second crust over the filling and seal the sides."
    },
    {
      "position": 10,
      "text": "Create holes on the secondary crust using a fork. This will serve as exhaust vents that will prevent the crust from deforming."
    },
    {
      "position": 11,
      "text": "Bake for 45 to 55 minutes or until the color turns golden brown. Note: Baking time may vary; make sure to check the color of the crust to determine if baking is complete."
    },
    {
      "position": 12,
      "text": "Let cool and serve. Share and enjoy!"
    }
  ],
  "servings": 6,
  "cooking_time_minutes": 55,
  "preparation_time_minutes": 10,
  "rest_time_minutes": null,
  "difficulty": "hard",
  "image_url": "https://github.com/ffimnsr/pepper-meal-recipes/raw/master/recipes/v1/assets/by-id/00127ffe-c2b9-5f75-840a-049ab3f083eb/cover.jpg",
  "video_url": null,
  "additional_media": [],
  "nutritional_information": {
    "@type": "NutritionInformation",
    "servingSize": "6 g"
  },
  "dietary_labels": [],
  "allergens": [],
  "equipment": [],
  "ingredients": [
    {
      "ingredient_id": "7ecff7d5-73ac-52f8-b020-2182bde86cbe",
      "name": "all-purpose flour",
      "normalized_name": "all-purpose flour",
      "quantity": "2",
      "unit": "cups",
      "preparation": null,
      "position": 1
    },
    {
      "ingredient_id": "bbfbf60f-39b8-5e5a-9815-eba35d54e9b9",
      "name": "butter",
      "normalized_name": "butter",
      "quantity": "1/3",
      "unit": "cup",
      "preparation": null,
      "position": 2
    },
    {
      "ingredient_id": "5158b18a-f73d-5768-a133-6b6c21cf5e98",
      "name": "salt",
      "normalized_name": "salt",
      "quantity": "1",
      "unit": "teaspoon",
      "preparation": null,
      "position": 3
    },
    {
      "ingredient_id": "ca246d64-68b3-5bd4-adcc-c82b62bb0ce8",
      "name": "vegetable shortening",
      "normalized_name": "vegetable shortening",
      "quantity": "1/3",
      "unit": "cup",
      "preparation": null,
      "position": 4
    },
    {
      "ingredient_id": "b94296dc-9e1a-5dad-9dc2-727ad66f0055",
      "name": "cold water",
      "normalized_name": "cold water",
      "quantity": "6 to 8",
      "unit": "tablespoons",
      "preparation": null,
      "position": 5
    },
    {
      "ingredient_id": "1d1653bc-204c-5d85-944b-98e0b614ce2a",
      "name": "young coconut meat",
      "normalized_name": "young coconut meat",
      "quantity": "2",
      "unit": "cups",
      "preparation": null,
      "position": 6
    },
    {
      "ingredient_id": "bdb57237-b976-59dd-abd1-dfb1d9e58253",
      "name": "granulated white sugar",
      "normalized_name": "granulated white sugar",
      "quantity": "3/4",
      "unit": "cup",
      "preparation": null,
      "position": 7
    },
    {
      "ingredient_id": "2ff09914-a7b1-5e13-ae56-ab72971ed01b",
      "name": "cornstarch diluted in 1/2 cup young coconut water",
      "normalized_name": "cornstarch diluted in 1/2 cup young coconut water",
      "quantity": "1/2",
      "unit": "cup",
      "preparation": null,
      "position": 8
    },
    {
      "ingredient_id": "478758cf-b8df-56ff-a79a-885f223169bb",
      "name": "evaporated milk",
      "normalized_name": "evaporated milk",
      "quantity": "1/2",
      "unit": "cup",
      "preparation": null,
      "position": 9
    }
  ],
  "categories": [
    {
      "id": "f478616f-a55d-517b-9b00-0fdd6d81e364",
      "slug": "dessert",
      "name": "Dessert"
    }
  ],
  "tags": [],
  "related_recipe_ids": [],
  "recipe_notes": [],
  "storage_notes": [],
  "source": {
    "name": "Panlasang Pinoy",
    "url": "https://panlasangpinoy.com/coconut-buko-pie-recipe/"
  },
  "public": true,
  "updated_at": 1280947960,
  "revision": 1
}
