{
  "$schema": "../../schemas/recipe.schema.json",
  "schema_version": 1,
  "id": "9cd698f7-e949-56c9-94ac-e934122d3c16",
  "slug": "shared-recipe-fruity-prune-cake",
  "name": "Fruity Prune Cake",
  "recipe_type": "dessert",
  "brief_description": "Fruity Prune cake Recipe. According to Carina, she used mango candy for this recipe to balance the sweetness of this luscious crusty prune cake.",
  "cuisine": null,
  "instructions": [
    {
      "position": 1,
      "text": "Soak prunes and mangoes overnight in brandy."
    },
    {
      "position": 2,
      "text": "Preheat the oven to 175 C"
    },
    {
      "position": 3,
      "text": "Cream the butter and then add egg, vanilla and water."
    },
    {
      "position": 4,
      "text": "Add in flour, baking powder and spices, mix well and then add the soaked prunes, mangoes and half of the chopped nuts, combine thoroughly using wooden spoon."
    },
    {
      "position": 5,
      "text": "Pour the mixture in 9inch round baking tin ( based and oil with greaseproof paper), topped with the other half of nuts and bake for 45min or until done."
    }
  ],
  "servings": 6,
  "cooking_time_minutes": null,
  "preparation_time_minutes": null,
  "rest_time_minutes": null,
  "difficulty": "easy",
  "image_url": "https://github.com/ffimnsr/pepper-meal-recipes/raw/master/recipes/v1/assets/by-id/9cd698f7-e949-56c9-94ac-e934122d3c16/cover.jpg",
  "video_url": null,
  "additional_media": [],
  "nutritional_information": null,
  "dietary_labels": [],
  "allergens": [],
  "equipment": [],
  "ingredients": [
    {
      "ingredient_id": "a41022c4-6f22-5e6c-9a47-2bf8db00a3e3",
      "name": "flour",
      "normalized_name": "flour",
      "quantity": "1 1/4",
      "unit": "cups",
      "preparation": null,
      "position": 1
    },
    {
      "ingredient_id": "2c01b926-610a-5149-9b15-e41677ad896e",
      "name": "baking powder",
      "normalized_name": "baking powder",
      "quantity": "1",
      "unit": "tablespoon",
      "preparation": null,
      "position": 2
    },
    {
      "ingredient_id": "83950f36-8f51-52c6-a4f4-63fba80765d4",
      "name": "light brown sugar",
      "normalized_name": "light brown sugar",
      "quantity": "1/2",
      "unit": "cup",
      "preparation": null,
      "position": 3
    },
    {
      "ingredient_id": "b1ea8e66-d743-5c83-a4cb-91b1d67eb9b6",
      "name": "sticks butter",
      "normalized_name": "sticks butter",
      "quantity": "2",
      "unit": null,
      "preparation": null,
      "position": 4
    },
    {
      "ingredient_id": "a2e0a342-573c-5860-b5b5-c67616650cc7",
      "name": "egg",
      "normalized_name": "egg",
      "quantity": "1",
      "unit": null,
      "preparation": null,
      "position": 5
    },
    {
      "ingredient_id": "b3093b3f-d99c-52fd-9035-976c0a2c55ea",
      "name": "water",
      "normalized_name": "water",
      "quantity": "2",
      "unit": "tablespoon",
      "preparation": null,
      "position": 6
    },
    {
      "ingredient_id": "188e0cea-6bd8-5e4a-b299-110121db099a",
      "name": "vanilla",
      "normalized_name": "vanilla",
      "quantity": "1",
      "unit": "teaspoon",
      "preparation": null,
      "position": 7
    },
    {
      "ingredient_id": "407c144b-d8f9-58a2-82b3-453a5cf0b58f",
      "name": "cinnamon and nutmeg",
      "normalized_name": "cinnamon and nutmeg",
      "quantity": null,
      "unit": null,
      "preparation": null,
      "position": 8
    },
    {
      "ingredient_id": "6eb570a6-a44f-5d5f-97cf-60d8e1d835d6",
      "name": "chopped prune",
      "normalized_name": "chopped prune",
      "quantity": "1",
      "unit": "cup",
      "preparation": null,
      "position": 9
    },
    {
      "ingredient_id": "00b6da5c-e022-5d6b-9c02-f5e5ffe1e4b3",
      "name": "chopped mango candy",
      "normalized_name": "chopped mango candy",
      "quantity": "1",
      "unit": "cup",
      "preparation": null,
      "position": 10
    },
    {
      "ingredient_id": "0395d79e-c1a7-5479-88bd-6a47c200ed08",
      "name": "raisin",
      "normalized_name": "raisin",
      "quantity": "1/2",
      "unit": "cup",
      "preparation": null,
      "position": 11
    },
    {
      "ingredient_id": "5e59af0d-6928-5cd7-bacc-cdedfc635327",
      "name": "chopped nut",
      "normalized_name": "chopped nut",
      "quantity": "1",
      "unit": "cup",
      "preparation": null,
      "position": 12
    },
    {
      "ingredient_id": "2511e36e-545d-5b30-97d7-e2df8acae4d4",
      "name": "brandy",
      "normalized_name": "brandy",
      "quantity": "3",
      "unit": "tablespoons",
      "preparation": null,
      "position": 13
    }
  ],
  "categories": [
    {
      "id": "f478616f-a55d-517b-9b00-0fdd6d81e364",
      "slug": "dessert",
      "name": "Dessert"
    }
  ],
  "tags": [],
  "related_recipe_ids": [],
  "recipe_notes": [],
  "storage_notes": [],
  "source": {
    "name": "Panlasang Pinoy",
    "url": "https://panlasangpinoy.com/shared-recipe-fruity-prune-cake/"
  },
  "public": true,
  "updated_at": 1297012737,
  "revision": 1
}
